yargs
